plotfish/__init__.py
plotfish-0.1.9.dist-info/WHEEL
plotfish-0.1.9.dist-info/METADATA
plotfish-0.1.9.dist-info/RECORD
