Metadata-Version: 2.1
Name: plotfish
Version: 0.1.9
Summary: Python SDK for Plotfish.
Author: The Fisherman
Requires-Python: >=3.9,<4.0
Classifier: Programming Language :: Python :: 3
Classifier: Programming Language :: Python :: 3.10
Classifier: Programming Language :: Python :: 3.9
Requires-Dist: python-socketio (>=5.7.2,<6.0.0)
Requires-Dist: requests (>=2.28.2,<3.0.0)
Requires-Dist: websocket-client (>=1.5.1,<2.0.0)
